rode_middleware/CORS.py
rode_middleware/Logging.py
rode_middleware/ProcessResponse.py
rode_middleware/__init__.py
RODE_middleware-1.0.1.dist-info/LICENSE.md
RODE_middleware-1.0.1.dist-info/METADATA
RODE_middleware-1.0.1.dist-info/WHEEL
RODE_middleware-1.0.1.dist-info/top_level.txt
RODE_middleware-1.0.1.dist-info/RECORD
